winternitz/__init__.py
winternitz/signatures.py
winternitz-1.0.2.dist-info/AUTHORS.rst
winternitz-1.0.2.dist-info/LICENSE.txt
winternitz-1.0.2.dist-info/METADATA
winternitz-1.0.2.dist-info/WHEEL
winternitz-1.0.2.dist-info/top_level.txt
winternitz-1.0.2.dist-info/RECORD
