Metadata-Version: 2.1
Name: winternitz
Version: 1.0.2
Summary: Python Winternitz One-Time-Signature(+) implementation
Home-page: https://github.com/sea212/winternitz-one-time-signature
Author: Harald Heckmann
Author-email: harald.heckmann93@web.de
License: mit
Platform: any
Classifier: Development Status :: 3 - Alpha
Classifier: Intended Audience :: Developers
Classifier: Intended Audience :: Science/Research
Classifier: License :: OSI Approved :: MIT License
Classifier: Natural Language :: English
Classifier: Operating System :: OS Independent
Classifier: Programming Language :: Python
Classifier: Programming Language :: Python :: 3 :: Only
Classifier: Programming Language :: Python :: 3.4
Classifier: Programming Language :: Python :: 3.5
Classifier: Programming Language :: Python :: 3.6
Classifier: Programming Language :: Python :: 3.7
Classifier: Topic :: Security :: Cryptography
Requires-Python: > 3.4
Provides-Extra: all
Requires-Dist: recommonmark ; extra == 'all'
Requires-Dist: sphinx (>=1.8) ; extra == 'all'
Requires-Dist: sphinx-rtd-theme ; extra == 'all'
Requires-Dist: isort ; extra == 'all'
Requires-Dist: flake8 ; extra == 'all'
Requires-Dist: pytest ; extra == 'all'
Requires-Dist: pytest-cov ; extra == 'all'
Requires-Dist: pytest-runner ; extra == 'all'
Requires-Dist: tox ; extra == 'all'
Provides-Extra: docs
Requires-Dist: recommonmark ; extra == 'docs'
Requires-Dist: sphinx ; extra == 'docs'
Requires-Dist: sphinx-rtd-theme ; extra == 'docs'
Provides-Extra: lint
Requires-Dist: isort ; extra == 'lint'
Requires-Dist: flake8 ; extra == 'lint'
Provides-Extra: testing
Requires-Dist: pytest ; extra == 'testing'
Requires-Dist: pytest-cov ; extra == 'testing'
Requires-Dist: pytest-runner ; extra == 'testing'
Requires-Dist: tox ; extra == 'testing'
